Workbook

Sheet APP
B10: CONFIGURAÇÕES
B11: Salário | D11: 7000
B12: Rendimento Carteira | D12: 0.008
B13: Sugestão de Investimento (30%) | D13: =D11*30% -> 2100
B15: INVESTIMENTO MENSAL
B16: Quanto investir por mês ? | D16: 700
B17: Por quantos anos ? | D17: 8
B18: Taxa de Rendimento mensal ? | D18: 0.01079
B19: Patrimônio acumulado ? | D19: =FV(D18,D17*12,D16*-1) -> 116896.92
B20: Dividendos mensais ? | D20: =D19*1% -> 1168.9692
B22: CENÁRIOS | D22: Dividendo
A23: 2 | B23: Acumalado em 2 anos ? | C23: =FV($D$18,A23*12,$D$16*-1) -> 19059.339 | D23: =C23*$D$12 -> 152.47471
A24: 5 | B24: Acumalado em 5 anos ? | C24: =FV($D$18,A24*12,$D$16*-1) -> 58643.84 | D24: =C24*$D$12 -> 469.15072
A25: 10 | B25: Acumalado em 10 anos ? | C25: =FV($D$18,A25*12,$D$16*-1) -> 170298.95 | D25: =C25*$D$12 -> 1362.3916
A26: 20 | B26: Acumalado em 20 anos ? | C26: =FV($D$18,A26*12,$D$16*-1) -> 787638.88 | D26: =C26*$D$12 -> 6301.111
A27: 30 | B27: Acumalado em 30 anos ? | C27: =FV($D$18,A27*12,$D$16*-1) -> 3025518.8 | D27: =C27*$D$12 -> 24204.15
B29: CENÁRIOS (investindo 30% salário) | D29: Dividendo
A30: 2 | B30: Acumalado em 2 anos ? | C30: =FV($D$18,A30*12,$D$13*-1) -> 57178.017 | D30: =C30*$D$12 -> 457.42414
A31: 5 | B31: Acumalado em 5 anos ? | C31: =FV($D$18,A31*12,$D$13*-1) -> 175931.52 | D31: =C31*$D$12 -> 1407.4522
A32: 10 | B32: Acumalado em 10 anos ? | C32: =FV($D$18,A32*12,$D$13*-1) -> 510896.85 | D32: =C32*$D$12 -> 4087.1748
A33: 20 | B33: Acumalado em 20 anos ? | C33: =FV($D$18,A33*12,$D$13*-1) -> 2362916.6 | D33: =C33*$D$12 -> 18903.333
A34: 30 | B34: Acumalado em 30 anos ? | C34: =FV($D$18,A34*12,$D$13*-1) -> 9076556.3 | D34: =C34*$D$12 -> 72612.45
B36: PERFIL | C36: CONSERVADOR
B37: VALOR A SER INVESTIDO POR MÊS | C37: =D16 -> 700
B39: TIPO DE FII | C39: Percentual Sugerido | D39: Valores
B40: PAPEL | C40: =VLOOKUP($C$36&"-"&B40,'Base de dados'!A:D,4,FALSE) -> 0.3 | D40: =$C$37*C40 -> 210
B41: TIJOLO | C41: =VLOOKUP($C$36&"-"&B41,'Base de dados'!A:D,4,FALSE) -> 0.5 | D41: =$C$37*C41 -> 350
B42: HÍBRIDOS | C42: =VLOOKUP($C$36&"-"&B42,'Base de dados'!A:D,4,FALSE) -> 0.1 | D42: =$C$37*C42 -> 70
B43: FOFs | C43: =VLOOKUP($C$36&"-"&B43,'Base de dados'!A:D,4,FALSE) -> 0.1 | D43: =$C$37*C43 -> 70
B44: DESENVOLVIMENTO | C44: =VLOOKUP($C$36&"-"&B44,'Base de dados'!A:D,4,FALSE) -> 0 | D44: =$C$37*C44 -> 0
B45: HOTELARIAS | C45: =VLOOKUP($C$36&"-"&B45,'Base de dados'!A:D,4,FALSE) -> 0 | D45: =$C$37*C45 -> 0
D46: =SUM(D40:D45) -> 700

Sheet Base de dados
A3: CHAVE | B3: PERFIL | C3: TIPO DE FII | D3: %
A4: =B4&"-"&C4 -> CONSERVADOR-PAPEL | B4: CONSERVADOR | C4: PAPEL | D4: 0.3
A5: =B5&"-"&C5 -> CONSERVADOR-TIJOLO | B5: CONSERVADOR | C5: TIJOLO | D5: 0.5
A6: =B6&"-"&C6 -> CONSERVADOR-HÍBRIDOS | B6: CONSERVADOR | C6: HÍBRIDOS | D6: 0.1
A7: =B7&"-"&C7 -> CONSERVADOR-FOFs | B7: CONSERVADOR | C7: FOFs | D7: 0.1
A8: =B8&"-"&C8 -> CONSERVADOR-DESENVOLVIMENTO | B8: CONSERVADOR | C8: DESENVOLVIMENTO | D8: 0
A9: =B9&"-"&C9 -> CONSERVADOR-HOTELARIAS | B9: CONSERVADOR | C9: HOTELARIAS | D9: 0
A10: =B10&"-"&C10 -> MODERADO-PAPEL | B10: MODERADO | C10: PAPEL | D10: 0.32
A11: =B11&"-"&C11 -> MODERADO-TIJOLO | B11: MODERADO | C11: TIJOLO | D11: 0.35
A12: =B12&"-"&C12 -> MODERADO-HÍBRIDOS | B12: MODERADO | C12: HÍBRIDOS | D12: 0.08
A13: =B13&"-"&C13 -> MODERADO-FOFs | B13: MODERADO | C13: FOFs | D13: 0.05
A14: =B14&"-"&C14 -> MODERADO-DESENVOLVIMENTO | B14: MODERADO | C14: DESENVOLVIMENTO | D14: 0.1
A15: =B15&"-"&C15 -> MODERADO-HOTELARIAS | B15: MODERADO | C15: HOTELARIAS | D15: 0.1
... A21: =B21&"-"&C21 -> AGRESSIVO-HOTELARIAS | B21: AGRESSIVO | C21: HOTELARIAS | D21: 0.1
